npc_samstim/__init__.py
npc_samstim/py.typed
npc_samstim/stim.py
npc_samstim/waveforms.py
npc_samstim-0.1.13.dist-info/licenses/LICENSE
npc_samstim-0.1.13.dist-info/METADATA
npc_samstim-0.1.13.dist-info/WHEEL
npc_samstim-0.1.13.dist-info/top_level.txt
npc_samstim-0.1.13.dist-info/RECORD
