Metadata-Version: 2.4
Name: npc-samstim
Version: 0.1.13
Summary: Tools for processing stim data from Sam's DynamicRoutingTask, compatible with data in the cloud.
Author-email: Ben Hardcastle <ben.hardcastle@alleninstitue.org>
License: MIT
Project-URL: Repository, https://github.com/AllenInstitute/npc_samstim
Project-URL: Issues, https://github.com/AllenInstitute/npc_samstim/issues
Classifier: Development Status :: 3 - Alpha
Classifier: Programming Language :: Python :: 3
Classifier: Programming Language :: Python :: 3.9
Classifier: Programming Language :: Python :: 3.10
Classifier: Programming Language :: Python :: 3.11
Classifier: License :: OSI Approved :: MIT License
Classifier: Operating System :: Microsoft :: Windows
Classifier: Operating System :: POSIX :: Linux
Requires-Python: >=3.9
License-File: LICENSE
Requires-Dist: DynamicRoutingTask>=0.1.91
Requires-Dist: npc-ephys>=0.1.1
Requires-Dist: numba>=0.59.0
Requires-Dist: npc-stim>=0.1.13
Requires-Dist: npc-sync>=0.1.3
Dynamic: license-file
